enochecker_cli/__init__.py
enochecker_cli/__main__.py
enochecker_cli/base.py
enochecker_cli/py.typed
enochecker_cli-0.7.1.dist-info/LICENSE
enochecker_cli-0.7.1.dist-info/METADATA
enochecker_cli-0.7.1.dist-info/WHEEL
enochecker_cli-0.7.1.dist-info/entry_points.txt
enochecker_cli-0.7.1.dist-info/top_level.txt
enochecker_cli-0.7.1.dist-info/RECORD
