Metadata-Version: 2.1
Name: enochecker_cli
Version: 0.7.1
Summary: Enochecker CLI
Home-page: https://github.com/enowars/enochecker_cli
Author: Benedikt Radtke
Author-email: benediktradtke@gmail.com
Classifier: Programming Language :: Python :: 3
Classifier: License :: OSI Approved :: MIT License
Classifier: Operating System :: OS Independent
Requires-Python: >=3.8
License-File: LICENSE
Requires-Dist: requests >=2.20
Requires-Dist: enochecker-core ==0.10.0
Requires-Dist: jsons >=1.0.0
